jupytercards/__init__.py
jupytercards/dynamic.py
jupytercards/flashcards.js
jupytercards/styles.css
jupytercards/svg-symbols.svg
jupytercards/swiped-events.min.js
jupytercards-3.2.1.dist-info/LICENSE
jupytercards-3.2.1.dist-info/WHEEL
jupytercards-3.2.1.dist-info/METADATA
jupytercards-3.2.1.dist-info/RECORD
