Metadata-Version: 2.1
Name: jupytercards
Version: 3.2.1
Summary: Module to display dynamic quizzes in Jupyter notebooks and Jupyter Books. Uses JavaScript to provide
Home-page: https://github.com/jmshea/jupytercards
Author: John M. Shea
Author-email: jshea@ieee.org
Classifier: License :: OSI Approved :: MIT License
